asyncio_task_logger/__init__.py
asyncio_task_logger/task_logger.py
asyncio_task_logger-0.0.2.dist-info/LICENSE
asyncio_task_logger-0.0.2.dist-info/METADATA
asyncio_task_logger-0.0.2.dist-info/WHEEL
asyncio_task_logger-0.0.2.dist-info/top_level.txt
asyncio_task_logger-0.0.2.dist-info/RECORD
