Metadata-Version: 2.1
Name: asyncio_task_logger
Version: 0.0.2
Summary: Allows logging on long running tasks that throw an exception but are still loaded into memory
Author-email: Quantlane <code@quantlane.com>, Jeremiah Payne <jeremiah@pinghajen.com>
Project-URL: Homepage, https://github.com/Pinghajen-Industries-LLC/asyncio-lask-logger
Project-URL: Bug Tracker, https://github.com/Pinghajen-Industries-LLC/asyncio-lask-logger/issues
Classifier: Programming Language :: Python :: 3
Classifier: License :: OSI Approved :: MIT License
Classifier: Operating System :: OS Independent
Requires-Python: >=3.7
License-File: LICENSE
